{
    "noSepsisFilesPath": "/home/mattyws/Documentos/mimic/data/no_sepsis_chartevents",
    "sepsisFilesPath": "/home/mattyws/Documentos/mimic/data/sepsis_chartevents",
    "modelCheckpointPath": "chartevents_checkpoint/",
    "modelConfigPath": "chartevents_checkpoint/config.json",
    "allDataPath" : "./data/",
    "trainingDataPath" :  "./dataTrainigChartevents/",
    "testingDataPath" : "./dataTestChartevents/",
    "datasetFilesFileName": "datasetFiles.pkl",
    "datasetLabelsFileName": "datasetLabels.pkl",
    "trainingGeneratorPath": "chartevents_checkpoint/dataTrainGenerator.pkl",
    "testingGeneratorPath": "chartevents_checkpoint/dataTestGenerator.pkl",
    "resultFilePath": "chartevents_checkpoint/result.csv",
    "hoursBeforeInfectionPoe" : 4,
    "dataLength" : null,
    "outputUnits": [
        64,
        32
    ],
    "numOutputNeurons": 1,
    "loss": "binary_crossentropy",
    "layersActivations": [
        "relu",
        "relu"
    ],
    "gru": true,
    "useDropout": true,
    "dropout": 0.3,
    "trainingEpochs": 30,
    "batchSize": 1
}
